adjust_client/__init__.py
adjust_client/client.py
adjust_client/config.py
adjust_client/exceptions.py
adjust_client-1.0.8.dist-info/METADATA
adjust_client-1.0.8.dist-info/WHEEL
adjust_client-1.0.8.dist-info/RECORD
