Metadata-Version: 2.1
Name: adjust-client
Version: 1.0.8
Summary: Adjust.com python API client
License: MIT
Author: Grebenshchikov Dmitry
Author-email: mtizima@gmail.com
Requires-Python: >=3.11,<4.0
Classifier: License :: OSI Approved :: MIT License
Classifier: Programming Language :: Python :: 3
Classifier: Programming Language :: Python :: 3.11
Classifier: Programming Language :: Python :: 3.12
Classifier: Programming Language :: Python :: 3.13
Requires-Dist: httpx (>=0.25.0,<0.26.0)
Requires-Dist: pydantic (>=2.8.2,<3.0.0)
Requires-Dist: tenacity (>=8.5.0,<9.0.0)
